<addons>
<addon id="plugin.program.legaceetv" name="Legacee TV" version="1.0.1" provider-name="LegaceeTV">
  <requires>
    <import addon="xbmc.python" version="2.1.0"/>
  </requires>
  <extension point="xbmc.python.pluginsource" library="default.py">
        <provides>program executable</provides>
  </extension>
  <extension point="xbmc.addon.metadata">
		<summary lang="en">Legacee TV</summary>
		<description lang="en">Easy Install of LegaceeTV Builds and Addons</description>
		<disclaimer lang="en">Note: we are not responsible or have any influence to the content and their availability from Kodi Add-ons</disclaimer>
		<platform>all</platform>
		<facebook>https://www.facebook.com/djlegacee</facebook>
		
	</extension>
</addon>


</addons>
